zkdex_python_sdk-0.1.2.dist-info/METADATA
zkdex_python_sdk-0.1.2.dist-info/WHEEL
zkdex_python_sdk/__init__.py
zkdex_python_sdk/zkdex_python_sdk.cpython-39-x86_64-linux-gnu.so
zkdex_python_sdk-0.1.2.dist-info/RECORD
